slimta/app/__init__.py
slimta/app/config.py
slimta/app/helpers.py
slimta/app/importutil.py
slimta/app/listeners.py
slimta/app/logging.py
slimta/app/lookup.py
slimta/app/main.py
slimta/app/setup.py
slimta/app/state.py
slimta/app/validation.py
slimta/app/etc/init-lsb.tmpl
slimta/app/etc/init-systemd.tmpl
slimta/app/etc/logging.yaml.sample
slimta/app/etc/slimta.yaml.sample
slimta-0.9.1.dist-info/LICENSE.md
slimta-0.9.1.dist-info/METADATA
slimta-0.9.1.dist-info/WHEEL
slimta-0.9.1.dist-info/entry_points.txt
slimta-0.9.1.dist-info/top_level.txt
slimta-0.9.1.dist-info/RECORD
