Metadata-Version: 2.1
Name: slimta
Version: 0.9.1
Summary: Configurable MTA based on the python-slimta library.
Home-page: http://slimta.org/
Author: Ian Good
Author-email: ian@icgood.net
License: MIT
Classifier: Development Status :: 3 - Alpha
Classifier: Topic :: Communications :: Email :: Mail Transport Agents
Classifier: Intended Audience :: Information Technology
Classifier: License :: OSI Approved :: MIT License
Classifier: Programming Language :: Python
Requires-Python: ~=3.11
License-File: LICENSE.md
Requires-Dist: python-slimta[spf] ~=5.0
Requires-Dist: pysasl <1.1
Requires-Dist: passlib
Requires-Dist: PyYAML
Provides-Extra: optional
Requires-Dist: python-slimta[aws,disk,redis] ~=5.0 ; extra == 'optional'
